schematic_db/__init__.py
schematic_db/db_schema/__init__.py
schematic_db/db_schema/db_schema.py
schematic_db/manifest_store/__init__.py
schematic_db/manifest_store/api_manifest_store.py
schematic_db/manifest_store/manifest_metadata_list.py
schematic_db/manifest_store/manifest_store.py
schematic_db/manifest_store/synapse_manifest_store.py
schematic_db/query_store/__init__.py
schematic_db/query_store/query_store.py
schematic_db/query_store/synapse_query_store.py
schematic_db/rdb/__init__.py
schematic_db/rdb/mysql.py
schematic_db/rdb/postgres.py
schematic_db/rdb/rdb.py
schematic_db/rdb/sql_alchemy_database.py
schematic_db/rdb/synapse_database.py
schematic_db/rdb_builder/__init__.py
schematic_db/rdb_builder/rdb_builder.py
schematic_db/rdb_queryer/__init__.py
schematic_db/rdb_queryer/rdb_queryer.py
schematic_db/rdb_updater/__init__.py
schematic_db/rdb_updater/rdb_updater.py
schematic_db/schema/__init__.py
schematic_db/schema/database_config.py
schematic_db/schema/schema.py
schematic_db/schema_graph/__init__.py
schematic_db/schema_graph/schema_graph.py
schematic_db/synapse/__init__.py
schematic_db/synapse/synapse.py
schematic_db/utils/__init__.py
schematic_db/utils/api_utils.py
schematic_db/utils/dataframe_utils.py
schematic_db/utils/types.py
schematic_db/utils/validators.py
schematic_db-0.1.6.dist-info/METADATA
schematic_db-0.1.6.dist-info/WHEEL
schematic_db-0.1.6.dist-info/RECORD
