Metadata-Version: 2.1
Name: schematic_db
Version: 0.1.6
Summary: 
Author: andrewelamb
Author-email: andrewelamb@gmail.com
Requires-Python: >=3.10,<4.0
Classifier: Programming Language :: Python :: 3
Classifier: Programming Language :: Python :: 3.10
Classifier: Programming Language :: Python :: 3.11
Classifier: Programming Language :: Python :: 3.12
Provides-Extra: dev
Provides-Extra: mysql
Provides-Extra: postgres
Provides-Extra: synapse
Requires-Dist: PyYAML (>=6.0,<7.0)
Requires-Dist: SQLAlchemy (>=2.0.19,<3.0.0)
Requires-Dist: SQLAlchemy-Utils (>=0.41.1,<0.42.0)
Requires-Dist: black (==24.4.0) ; extra == "dev"
Requires-Dist: coverage (>=7.2.0,<8.0.0) ; extra == "dev"
Requires-Dist: deprecation (>=2.1.0,<3.0.0)
Requires-Dist: interrogate (>=1.5.0,<2.0.0) ; extra == "dev"
Requires-Dist: mypy (>=1.9.0,<2.0.0) ; extra == "dev"
Requires-Dist: mypy-extensions (>=1.0.0,<2.0.0) ; extra == "dev"
Requires-Dist: mysqlclient (>=2.1.1,<3.0.0) ; extra == "mysql"
Requires-Dist: networkx (>=3.3.0,<4.0.0)
Requires-Dist: pandas (>=2.0.0,<3.0.0)
Requires-Dist: pdoc (>=14.0.0,<15.0.0) ; extra == "dev"
Requires-Dist: psycopg2-binary (>=2.9.5,<3.0.0) ; extra == "postgres"
Requires-Dist: pydantic (>=2.7.0,<3.0.0)
Requires-Dist: pylint (>=3.1.0,<4.0.0) ; extra == "dev"
Requires-Dist: pytest (>=8.0.0,<9.0.0) ; extra == "dev"
Requires-Dist: pytest-mock (>=3.10.0,<4.0.0) ; extra == "dev"
Requires-Dist: requests (>=2.28.1,<3.0.0)
Requires-Dist: synapseclient (>=4.1.0,<5.0.0) ; extra == "synapse"
Requires-Dist: tenacity (>=9.0.0,<10.0.0)
Requires-Dist: validators (>=0.29.0,<0.30.0)
